imapotatoes11/__init__.py
imapotatoes11/timed.py
imapotatoes11-0.0.2.dist-info/METADATA
imapotatoes11-0.0.2.dist-info/WHEEL
imapotatoes11-0.0.2.dist-info/licenses/LICENSE
imapotatoes11-0.0.2.dist-info/RECORD
