Metadata-Version: 2.1
Name: imapotatoes11
Version: 0.0.2
Summary: why are you here
Project-URL: Homepage, https://github.com/imapotatoes11/imapotatoes11
Project-URL: Bug Tracker, https://rickrollredirect.github.io
Author-email: imapotatoes11 <imapotatoes11@gmail.com>
License-File: LICENSE
Classifier: License :: OSI Approved :: MIT License
Classifier: Operating System :: OS Independent
Classifier: Programming Language :: Python :: 3
Requires-Python: >=3.7
